{
  "ui": {
    "border_primary": "#cfbdfe",
    "border_secondary": "#ccc2db",
    "header_background": "#cfbdfe",
    "header_text": "#36275d",
    "footer_background": "#141218",
    "footer_text": "#cac4cf",
    "text_primary": "#e6e0e9",
    "text_secondary": "#cac4cf",
    "text_accent": "#cfbdfe",
    "selection_background": "#cfbdfe",
    "selection_text": "#36275d"
  },
  "charts": {
    "network_download": "#cfbdfe",
    "network_upload": "#4d3d75",
    "network_line": "#ccc2db",
    "cpu_core_low": "#4d3d75",
    "cpu_core_medium": "#cfbdfe",
    "cpu_core_high": "#efb8c8",
    "disk_read": "#cfbdfe",
    "disk_write": "#4d3d75"
  },
  "progress_bars": {
    "memory_low": "#4d3d75",
    "memory_medium": "#cfbdfe",
    "memory_high": "#efb8c8",
    "disk_low": "#4d3d75",
    "disk_medium": "#cfbdfe",
    "disk_high": "#efb8c8",
    "cpu_low": "#4d3d75",
    "cpu_medium": "#cfbdfe",
    "cpu_high": "#efb8c8",
    "progress_background": "#211f24"
  },
  "temperature": {
    "cold": "#4d3d75",
    "warm": "#cfbdfe",
    "hot": "#efb8c8",
    "danger": "#ffb4ab"
  },
  "status": {
    "success": "#22C55E",
    "warning": "#F59E0B",
    "error": "#ffb4ab",
    "info": "#cfbdfe"
  }
}
